ae/lockname.py
ae_lockname-0.3.9.dist-info/LICENSE.md
ae_lockname-0.3.9.dist-info/METADATA
ae_lockname-0.3.9.dist-info/WHEEL
ae_lockname-0.3.9.dist-info/top_level.txt
ae_lockname-0.3.9.dist-info/zip-safe
ae_lockname-0.3.9.dist-info/RECORD
